MANIFEST.in
setup.py
torchsparseattn/__init__.py
torchsparseattn/_fused.c
torchsparseattn/_fused.pyx
torchsparseattn/_fused_jv.c
torchsparseattn/_fused_jv.pyx
torchsparseattn/_isotonic.c
torchsparseattn/_isotonic.pyx
torchsparseattn/base.py
torchsparseattn/fused.py
torchsparseattn/isotonic.py
torchsparseattn/oscar.py
torchsparseattn/sparsemax.py
torchsparseattn/test_attention.py
torchsparseattn/test_fused.py
torchsparseattn/test_oscar.py
torchsparseattn/test_sparsemax.py
torchsparseattn.egg-info/PKG-INFO
torchsparseattn.egg-info/SOURCES.txt
torchsparseattn.egg-info/dependency_links.txt
torchsparseattn.egg-info/not-zip-safe
torchsparseattn.egg-info/requires.txt
torchsparseattn.egg-info/top_level.txt