Metadata-Version: 1.1
Name: torchsparseattn
Version: 0.2
Summary: Sparse structured attention mechanisms for pytorch
Home-page: UNKNOWN
Author: Vlad Niculae
Author-email: vlad@vene.ro
License: BSD 3-clause
Platform: UNKNOWN
Classifier: Intended Audience :: Science/Research
Classifier: Intended Audience :: Developers
Classifier: License :: OSI Approved
Classifier: Programming Language :: C
Classifier: Programming Language :: Python
Classifier: Topic :: Software Development
Classifier: Topic :: Scientific/Engineering
Classifier: Operating System :: Microsoft :: Windows
Classifier: Operating System :: POSIX
Classifier: Operating System :: Unix
Classifier: Operating System :: MacOS
